{
  "fill" : "system-dark",
  "groups" : [
    {
      "blend-mode" : "normal",
      "blur-material" : null,
      "layers" : [
        {
          "image-name" : "SvgTrace-File Name-2.svg",
          "name" : "SvgTrace-File Name-2"
        }
      ],
      "lighting" : "individual",
      "opacity" : 1,
      "shadow" : {
        "kind" : "neutral",
        "opacity" : 0.5
      },
      "translucency" : {
        "enabled" : true,
        "value" : 0.5
      }
    }
  ],
  "supported-platforms" : {
    "circles" : [
      "watchOS"
    ],
    "squares" : "shared"
  }
}